pyistp/__init__.py
pyistp/_impl.py
pyistp/data_variable.py
pyistp/loader.py
pyistp/support_data_variable.py
pyistp/drivers/__init__.py
pyistp/drivers/_driver.py
pyistp/drivers/pycdfpp.py
pyistp/drivers/spacepy.py
pyistp-0.7.2.dist-info/licenses/COPYING
pyistp-0.7.2.dist-info/WHEEL
pyistp-0.7.2.dist-info/METADATA
pyistp-0.7.2.dist-info/RECORD
