Metadata-Version: 2.4
Name: pyistp
Version: 0.7.2
Summary: An easy to use ISTP loader package.
Keywords: satellite,plasma-physics,nasa-data,amda,cdpp,CDF
Author-email: Alexis Jeandet <alexis.jeandet@member.fsf.org>
Maintainer-email: Alexis Jeandet <alexis.jeandet@member.fsf.org>
Requires-Python: >=3.8
Classifier: Development Status :: 4 - Beta
Classifier: Intended Audience :: Science/Research
Classifier: License :: OSI Approved :: GNU General Public License v3 (GPLv3)
Classifier: Natural Language :: English
Classifier: Programming Language :: Python :: 3
Classifier: Programming Language :: Python :: 3.8
Classifier: Programming Language :: Python :: 3.9
Classifier: Programming Language :: Python :: 3.10
Classifier: Programming Language :: Python :: 3.11
Classifier: Programming Language :: Python :: 3.12
License-File: COPYING
Requires-Dist: pycdfpp>=0.6.0
Project-URL: documentation, https://pyistp.readthedocs.io/en/latest/
Project-URL: homepage, https://github.com/SciQLop/PyISTP
Project-URL: repository, https://github.com/SciQLop/PyISTP
